rci_gg/__init__.py
rci_gg/core.py
rci_gg/data/__init__.py
rci_gg/data/all_DL.txt
rci_gg-0.1.3.dist-info/METADATA
rci_gg-0.1.3.dist-info/WHEEL
rci_gg-0.1.3.dist-info/top_level.txt
rci_gg-0.1.3.dist-info/RECORD
