Metadata-Version: 2.2
Name: rci_gg
Version: 0.1.3
Summary: RCI - модуль для работы с ячейками кода
Classifier: Programming Language :: Python :: 3
Classifier: License :: OSI Approved :: MIT License
Classifier: Operating System :: OS Independent
Requires-Python: >=3.6
Dynamic: classifier
Dynamic: description-content-type
Dynamic: requires-python
Dynamic: summary
